AUTHORS.rst
CONTRIBUTING.rst
HISTORY.rst
LICENSE
MANIFEST.in
README.rst
setup.cfg
setup.py
docs/Makefile
docs/authors.rst
docs/conf.py
docs/contributing.rst
docs/farepa.rst
docs/history.rst
docs/index.rst
docs/installation.rst
docs/make.bat
docs/modules.rst
docs/readme.rst
docs/usage.rst
docs/_build/html/_static/ajax-loader.gif
docs/_build/html/_static/comment-bright.png
docs/_build/html/_static/comment-close.png
docs/_build/html/_static/comment.png
docs/_build/html/_static/down-pressed.png
docs/_build/html/_static/down.png
docs/_build/html/_static/file.png
docs/_build/html/_static/minus.png
docs/_build/html/_static/plus.png
docs/_build/html/_static/up-pressed.png
docs/_build/html/_static/up.png
farepa/__init__.py
farepa/cli.py
farepa/farepa.py
farepa.egg-info/PKG-INFO
farepa.egg-info/SOURCES.txt
farepa.egg-info/dependency_links.txt
farepa.egg-info/entry_points.txt
farepa.egg-info/not-zip-safe
farepa.egg-info/requires.txt
farepa.egg-info/top_level.txt
tests/test_farepa.py